fmtutil/__about__.py
fmtutil/__init__.py
fmtutil/__main__.py
fmtutil/__type.py
fmtutil/__version.py
fmtutil/cli.py
fmtutil/exceptions.py
fmtutil/formatter.py
fmtutil/utils.py
fmtutil-1.0.15.dist-info/METADATA
fmtutil-1.0.15.dist-info/WHEEL
fmtutil-1.0.15.dist-info/entry_points.txt
fmtutil-1.0.15.dist-info/licenses/LICENSE
fmtutil-1.0.15.dist-info/RECORD
