Metadata-Version: 2.4
Name: fmtutil
Version: 1.0.15
Summary: Lightweight formatter objects
Project-URL: Homepage, https://github.com/korawica/fmtutil/
Project-URL: Source Code, https://github.com/korawica/fmtutil/
Author-email: korawica <korawich.anu@gmail.com>
License-Expression: MIT
License-File: LICENSE
Keywords: formatter,utility
Classifier: Development Status :: 5 - Production/Stable
Classifier: Natural Language :: English
Classifier: Operating System :: OS Independent
Classifier: Programming Language :: Python
Classifier: Programming Language :: Python :: 3 :: Only
Classifier: Programming Language :: Python :: 3.9
Classifier: Programming Language :: Python :: 3.10
Classifier: Programming Language :: Python :: 3.11
Classifier: Programming Language :: Python :: 3.12
Classifier: Programming Language :: Python :: 3.13
Classifier: Topic :: Utilities
Requires-Python: >=3.9.0
Provides-Extra: docs
Requires-Dist: mkdocs-awesome-pages-plugin; extra == 'docs'
Requires-Dist: mkdocs-material; extra == 'docs'
Provides-Extra: python-dateutil
Requires-Dist: python-dateutil<3.0.0,>=2.8.2; extra == 'python-dateutil'
Requires-Dist: types-python-dateutil==2.9.0.20241206; extra == 'python-dateutil'
Provides-Extra: test
Requires-Dist: python-dateutil<3.0.0,>=2.8.2; extra == 'test'
Requires-Dist: types-python-dateutil==2.9.0.20241206; extra == 'test'
Requires-Dist: typing-extensions; extra == 'test'
